{
  "permalink": "/blog/一篇文章总结Vue3中的路由与路由配置",
  "editUrl": "https://git.7wate.com/zhouzhongping/wiki/src/branch/master/blog/一篇文章总结Vue3中的路由与路由配置.md",
  "source": "@site/blog\\一篇文章总结Vue3中的路由与路由配置.md",
  "title": "一篇文章总结Vue3中的路由与路由配置",
  "description": "路由的基本配置",
  "date": "2021-12-19T00:00:00.000Z",
  "formattedDate": "2021年12月19日",
  "tags": [
    {
      "label": "Vue",
      "permalink": "/blog/tags/vue"
    }
  ],
  "readingTime": 5.405,
  "hasTruncateMarker": false,
  "authors": [
    {
      "name": "Justin"
    }
  ],
  "frontMatter": {
    "title": "一篇文章总结Vue3中的路由与路由配置",
    "date": "2021-12-19T00:00:00.000Z",
    "author": "Justin",
    "top": false,
    "cover": false,
    "categories": "Vue",
    "tags": [
      "Vue"
    ]
  },
  "prevItem": {
    "title": "一文带你学习：Vue生命周期、this.$nextTick、将Axios绑定到全局、输入防抖",
    "permalink": "/blog/一文带你学习：Vue生命周期、this.$nextTick、将Axios绑定到全局、输入防抖"
  },
  "nextItem": {
    "title": "这一次，彻底搞懂箭头函数",
    "permalink": "/blog/这一次，彻底搞懂箭头函数"
  }
}