{
  "permalink": "/blog/Egg.js中间件进行登录鉴权的核心思路",
  "editUrl": "https://git.7wate.com/zhouzhongping/wiki/src/branch/master/blog/Egg.js中间件进行登录鉴权的核心思路.md",
  "source": "@site/blog/Egg.js中间件进行登录鉴权的核心思路.md",
  "title": "Egg.js中间件进行登录鉴权的核心思路",
  "description": "无论是在实际项目中还是在面试中，只要涉及到项目的问题，注册登录如何验证的问题，总是面试官的宠儿，这一次让我们来系统性的梳理如何完成一次登录的验证。（注意：项目实现的基础是以Egg.js作为后台实现的）",
  "date": "2021-11-13T00:00:00.000Z",
  "formattedDate": "2021年11月13日",
  "tags": [
    {
      "label": "Egg.js",
      "permalink": "/blog/tags/egg-js"
    }
  ],
  "readingTime": 4,
  "hasTruncateMarker": false,
  "authors": [
    {
      "name": "Justin"
    }
  ],
  "frontMatter": {
    "title": "Egg.js中间件进行登录鉴权的核心思路",
    "date": "2021-11-13T00:00:00.000Z",
    "author": "Justin",
    "top": false,
    "cover": false,
    "categories": "Egg.js",
    "tags": [
      "Egg.js"
    ]
  },
  "prevItem": {
    "title": "使用JS打印九九乘法表",
    "permalink": "/blog/使用JS打印九九乘法表"
  },
  "nextItem": {
    "title": "LeetCode——K个一组翻转链表（三指针）",
    "permalink": "/blog/LeetCode——K个一组翻转链表（三指针）"
  }
}