{
  "permalink": "/blog/Vue的作用域插槽slot有什么用？",
  "editUrl": "https://git.7wate.com/zhouzhongping/wiki/src/branch/master/blog/Vue的作用域插槽slot有什么用？.md",
  "source": "@site/blog/Vue的作用域插槽slot有什么用？.md",
  "title": "Vue的作用域插槽slot有什么用？",
  "description": "一、基本使用",
  "date": "2022-04-27T00:00:00.000Z",
  "formattedDate": "2022年4月27日",
  "tags": [
    {
      "label": "Vue",
      "permalink": "/blog/tags/vue"
    }
  ],
  "readingTime": 1.185,
  "hasTruncateMarker": false,
  "authors": [
    {
      "name": "Justin"
    }
  ],
  "frontMatter": {
    "title": "Vue的作用域插槽slot有什么用？",
    "date": "2022-04-27T00:00:00.000Z",
    "author": "Justin",
    "top": false,
    "cover": false,
    "categories": "Vue",
    "tags": [
      "Vue"
    ]
  },
  "prevItem": {
    "title": "你了解Vue的动态加载组件和异步加载组件吗？",
    "permalink": "/blog/你了解Vue的动态加载组件和异步加载组件吗？"
  },
  "nextItem": {
    "title": "你真的了解Vue的生命周期吗？",
    "permalink": "/blog/你真的了解Vue的生命周期吗？"
  }
}