{
  "permalink": "/blog/ES6——24：函数的调用方式",
  "editUrl": "https://git.7wate.com/zhouzhongping/wiki/src/branch/master/blog/ES6——24：函数的调用方式.md",
  "source": "@site/blog\\ES6——24：函数的调用方式.md",
  "title": "ES6——24：函数的调用方式",
  "description": "1：普通函数",
  "date": "2021-03-16T00:00:00.000Z",
  "formattedDate": "2021年3月16日",
  "tags": [
    {
      "label": "ES6",
      "permalink": "/blog/tags/es-6"
    }
  ],
  "readingTime": 0.235,
  "hasTruncateMarker": false,
  "authors": [],
  "frontMatter": {
    "title": "ES6——24：函数的调用方式",
    "date": "2021-03-16T00:00:00.000Z",
    "categories": "ES6",
    "tags": [
      "ES6"
    ]
  },
  "prevItem": {
    "title": "ES6——24：函数内部的this指向",
    "permalink": "/blog/ES6——24：函数内部的this指向"
  },
  "nextItem": {
    "title": "ES6——25：函数内部this指向的三种方法",
    "permalink": "/blog/ES6——25：函数内部this指向的三种方法"
  }
}