{
  "permalink": "/blog/解决OBS录屏软件窗口采集不全的问题",
  "editUrl": "https://git.7wate.com/zhouzhongping/wiki/src/branch/master/blog/解决OBS录屏软件窗口采集不全的问题.md",
  "source": "@site/blog\\解决OBS录屏软件窗口采集不全的问题.md",
  "title": "解决OBS录屏软件窗口采集不全的问题",
  "description": "问题描述",
  "date": "2021-03-31T00:00:00.000Z",
  "formattedDate": "2021年3月31日",
  "tags": [
    {
      "label": "debug",
      "permalink": "/blog/tags/debug"
    }
  ],
  "readingTime": 0.26,
  "hasTruncateMarker": false,
  "authors": [],
  "frontMatter": {
    "title": "解决OBS录屏软件窗口采集不全的问题",
    "date": "2021-03-31T00:00:00.000Z",
    "categories": "debug",
    "tags": [
      "debug"
    ]
  },
  "prevItem": {
    "title": "LeetCode——替换空格",
    "permalink": "/blog/LeetCode——替换空格"
  },
  "nextItem": {
    "title": "axios基础（六）：axios取消请求",
    "permalink": "/blog/axios基础（六）：axios取消请求"
  }
}