{
  "permalink": "/blog/React中setState不起作用的情况",
  "editUrl": "https://git.7wate.com/zhouzhongping/wiki/src/branch/master/blog/React中setState不起作用的情况.md",
  "source": "@site/blog\\React中setState不起作用的情况.md",
  "title": "React中setState不起作用的情况",
  "description": "看下面这个案例",
  "date": "2021-04-30T00:00:00.000Z",
  "formattedDate": "2021年4月30日",
  "tags": [
    {
      "label": "React",
      "permalink": "/blog/tags/react"
    }
  ],
  "readingTime": 0.465,
  "hasTruncateMarker": false,
  "authors": [],
  "frontMatter": {
    "title": "React中setState不起作用的情况",
    "date": "2021-04-30T00:00:00.000Z",
    "categories": "React",
    "tags": [
      "React"
    ]
  },
  "prevItem": {
    "title": "React-60：render props",
    "permalink": "/blog/React-60：render props"
  },
  "nextItem": {
    "title": "React报错：Element type is invali expected a string or a class",
    "permalink": "/blog/React报错：Element type is invali expected a string or a class"
  }
}