{
  "permalink": "/blog/Egg.js中使用extend、Cookie、Session的基本方式",
  "editUrl": "https://git.7wate.com/zhouzhongping/wiki/src/branch/master/blog/Egg.js中使用extend、Cookie、Session的基本方式.md",
  "source": "@site/blog\\Egg.js中使用extend、Cookie、Session的基本方式.md",
  "title": "Egg.js中使用extend、Cookie、Session的基本方式",
  "description": "一、初始化",
  "date": "2021-10-29T00:00:00.000Z",
  "formattedDate": "2021年10月29日",
  "tags": [
    {
      "label": "Egg.js",
      "permalink": "/blog/tags/egg-js"
    }
  ],
  "readingTime": 6.845,
  "hasTruncateMarker": false,
  "authors": [
    {
      "name": "Justin"
    }
  ],
  "frontMatter": {
    "title": "Egg.js中使用extend、Cookie、Session的基本方式",
    "date": "2021-10-29T00:00:00.000Z",
    "author": "Justin",
    "top": false,
    "cover": false,
    "categories": "Egg.js",
    "tags": [
      "Egg.js"
    ]
  },
  "prevItem": {
    "title": "Egg.js中间件的核心用法",
    "permalink": "/blog/Egg.js中间件的核心用法"
  },
  "nextItem": {
    "title": "LeetCode——二叉树的层序遍历（递归与非递归）",
    "permalink": "/blog/LeetCode——二叉树的层序遍历（递归与非递归）"
  }
}